lsst/ts/salobj/__init__.py
lsst/ts/salobj/async_s3_bucket.py
lsst/ts/salobj/base.py
lsst/ts/salobj/base_config_test_case.py
lsst/ts/salobj/base_csc.py
lsst/ts/salobj/base_csc_test_case.py
lsst/ts/salobj/base_script.py
lsst/ts/salobj/config_schema.py
lsst/ts/salobj/configurable_csc.py
lsst/ts/salobj/controller.py
lsst/ts/salobj/csc_commander.py
lsst/ts/salobj/csc_utils.py
lsst/ts/salobj/dds_utils.py
lsst/ts/salobj/domain.py
lsst/ts/salobj/idl_metadata.py
lsst/ts/salobj/remote.py
lsst/ts/salobj/sal_enums.py
lsst/ts/salobj/sal_info.py
lsst/ts/salobj/sal_log_handler.py
lsst/ts/salobj/testcsc.py
lsst/ts/salobj/testcsccommander.py
lsst/ts/salobj/testscript.py
lsst/ts/salobj/testutils.py
lsst/ts/salobj/type_hints.py
lsst/ts/salobj/validator.py
lsst/ts/salobj/version.py
lsst/ts/salobj/topics/__init__.py
lsst/ts/salobj/topics/base_topic.py
lsst/ts/salobj/topics/controller_command.py
lsst/ts/salobj/topics/controller_event.py
lsst/ts/salobj/topics/controller_telemetry.py
lsst/ts/salobj/topics/read_topic.py
lsst/ts/salobj/topics/remote_command.py
lsst/ts/salobj/topics/remote_event.py
lsst/ts/salobj/topics/remote_telemetry.py
lsst/ts/salobj/topics/write_topic.py
ts_salobj-6.9.1.data/data/lib/python3.8/schema/Test.yaml
ts_salobj-6.9.1.data/scripts/command_test_csc.py
ts_salobj-6.9.1.data/scripts/run_test_csc.py
ts_salobj-6.9.1.dist-info/LICENSE
ts_salobj-6.9.1.dist-info/METADATA
ts_salobj-6.9.1.dist-info/WHEEL
ts_salobj-6.9.1.dist-info/top_level.txt
ts_salobj-6.9.1.dist-info/RECORD
