Metadata-Version: 2.1
Name: ts-salobj
Version: 6.9.1
Summary: Object-oriented interface to LSST SAL communications middleware.
Home-page: UNKNOWN
License: GPL
Project-URL: Bug Tracker, https://jira.lsstcorp.org/secure/Dashboard.jspa
Project-URL: Source Code, https://github.com/lsst-ts/ts_salobj
Platform: UNKNOWN
Requires-Dist: numpy
Requires-Dist: astropy
Requires-Dist: boto3
Requires-Dist: ts-dds
Requires-Dist: ts-ddsconfig
Requires-Dist: ts-idl (>=1.2)
Requires-Dist: ts-utils
Provides-Extra: dev
Requires-Dist: numpy ; extra == 'dev'
Requires-Dist: astropy ; extra == 'dev'
Requires-Dist: boto3 ; extra == 'dev'
Requires-Dist: ts-dds ; extra == 'dev'
Requires-Dist: ts-ddsconfig ; extra == 'dev'
Requires-Dist: ts-idl (>=1.2) ; extra == 'dev'
Requires-Dist: ts-utils ; extra == 'dev'
Requires-Dist: documenteer[pipelines] ; extra == 'dev'
